sdk/__init__.py
sdk/authentication.py
sdk/eligibility_apis.py
sdk/offers.py
sdk/orders.py
sdk/payment_links.py
sdk/payments.py
sdk/pgreconciliation.py
sdk/refunds.py
sdk/sdk.py
sdk/sdkconfiguration.py
sdk/settlement_reconciliation.py
sdk/settlements.py
sdk/softpos.py
sdk/token_vault.py
sdk/models/__init__.py
sdk/models/callbacks/__init__.py
sdk/models/callbacks/createorder.py
sdk/models/errors/__init__.py
sdk/models/errors/sdkerror.py
sdk/models/operations/__init__.py
sdk/models/operations/cancelpaymentlink.py
sdk/models/operations/createoffer.py
sdk/models/operations/createorder.py
sdk/models/operations/createpaymentlink.py
sdk/models/operations/createrefund.py
sdk/models/operations/createterminals.py
sdk/models/operations/deletespecificsavedinstrument.py
sdk/models/operations/eligibilitycardlessemi.py
sdk/models/operations/eligibilityoffer.py
sdk/models/operations/eligibilitypaylater.py
sdk/models/operations/fetchallsavedinstruments.py
sdk/models/operations/fetchcryptogram.py
sdk/models/operations/fetchspecificsavedinstrument.py
sdk/models/operations/getallrefundsfororder.py
sdk/models/operations/getoffer.py
sdk/models/operations/getorder.py
sdk/models/operations/getpaymentbyid.py
sdk/models/operations/getpaymentlinkdetails.py
sdk/models/operations/getpaymentlinkorders.py
sdk/models/operations/getpaymentsfororder.py
sdk/models/operations/getrefund.py
sdk/models/operations/getsettlements.py
sdk/models/operations/getterminalbymobilenumber.py
sdk/models/operations/orderpay.py
sdk/models/operations/otprequest.py
sdk/models/operations/pgreconciliation.py
sdk/models/operations/preauthorization.py
sdk/models/operations/settlementreconciliation.py
sdk/models/operations/settlements.py
sdk/models/shared/__init__.py
sdk/models/shared/all.py
sdk/models/shared/apierror.py
sdk/models/shared/app.py
sdk/models/shared/apppaymentmethod.py
sdk/models/shared/authenticationerror.py
sdk/models/shared/authorizationinpaymentsentity.py
sdk/models/shared/authorizationrequest.py
openapi_suhas_test-0.1.0.dist-info/METADATA
openapi_suhas_test-0.1.0.dist-info/WHEEL
openapi_suhas_test-0.1.0.dist-info/top_level.txt
openapi_suhas_test-0.1.0.dist-info/RECORD
